abyss_sdk/__init__.py
abyss_sdk/client.py
abyss_sdk/error_handler.py
abyss_sdk/errors.py
abyss_sdk-0.1.0.dist-info/METADATA
abyss_sdk-0.1.0.dist-info/WHEEL
abyss_sdk-0.1.0.dist-info/top_level.txt
abyss_sdk-0.1.0.dist-info/RECORD
