Metadata-Version: 2.1
Name: abyss-sdk
Version: 0.1.0
Summary: UNKNOWN
Home-page: https://github.com/xtracthub/abyss
Author: Ryan Wong
Author-email: rewong03@uchicago.edu
License: UNKNOWN
Platform: UNKNOWN
Requires-Dist: requests
